pyvfp64/__init__.py
pyvfp64/connection.py
pyvfp64/dialect.py
pyvfp64/pyvfp.py
pyvfp64/utils.py
pyvfp64/v_types.py
pyvfp64/bin/vfp_to_json.exe
pyvfp64-0.0.6.2.dist-info/METADATA
pyvfp64-0.0.6.2.dist-info/WHEEL
pyvfp64-0.0.6.2.dist-info/top_level.txt
pyvfp64-0.0.6.2.dist-info/RECORD
