Metadata-Version: 2.4
Name: pyvfp64
Version: 0.0.6.2
Summary: A Python wrapper for vfp_to_json.exe to convert VFP data to pandas DataFrame
Author: Lewis Morris
Author-email: lewis@arched.dev
Classifier: Programming Language :: Python :: 3
Classifier: Operating System :: Microsoft :: Windows
Classifier: License :: OSI Approved :: MIT License
Classifier: Topic :: Database
Requires-Python: >=3.6
Requires-Dist: pandas
Dynamic: author
Dynamic: author-email
Dynamic: classifier
Dynamic: requires-dist
Dynamic: requires-python
Dynamic: summary
